tno/quantum/optimization/qubo/components/__init__.py
tno/quantum/optimization/qubo/components/_freq.py
tno/quantum/optimization/qubo/components/_qubo.py
tno/quantum/optimization/qubo/components/py.typed
tno/quantum/optimization/qubo/components/_postprocessing/_postprocessor.py
tno/quantum/optimization/qubo/components/_postprocessing/_postprocessor_config.py
tno/quantum/optimization/qubo/components/_preprocessing/_partial_solution.py
tno/quantum/optimization/qubo/components/_preprocessing/_preprocessor.py
tno/quantum/optimization/qubo/components/_preprocessing/_preprocessor_config.py
tno/quantum/optimization/qubo/components/_results/_basic_result.py
tno/quantum/optimization/qubo/components/_results/_result_interface.py
tno/quantum/optimization/qubo/components/_solvers/_solver.py
tno/quantum/optimization/qubo/components/_solvers/_solver_config.py
tno/quantum/optimization/qubo/components/test/__init__.py
tno/quantum/optimization/qubo/components/test/test_freq.py
tno/quantum/optimization/qubo/components/test/test_partial_solution.py
tno/quantum/optimization/qubo/components/test/test_qubo.py
tno/quantum/optimization/qubo/components/test/test_result_interface.py
tno/quantum/optimization/qubo/components/test/test_solver.py
tno/quantum/optimization/qubo/components/test/test_solver_config.py
tno_quantum_optimization_qubo_components-1.2.0.dist-info/licenses/LICENSE
tno_quantum_optimization_qubo_components-1.2.0.dist-info/METADATA
tno_quantum_optimization_qubo_components-1.2.0.dist-info/WHEEL
tno_quantum_optimization_qubo_components-1.2.0.dist-info/top_level.txt
tno_quantum_optimization_qubo_components-1.2.0.dist-info/RECORD
